pcviewer/__init__.py
pcviewer/http_server.py
pcviewer/run.py
pcviewer/server.py
pcviewer/static/index.html
pcviewer/static/viewer.js
pcviewer/static/js/FlyControls.js
pcviewer/static/js/OrbitControls.js
pcviewer/static/js/TrackballControls.js
pcviewer/static/js/three.min.js
pcviewer-0.1.2.dist-info/LICENSE
pcviewer-0.1.2.dist-info/METADATA
pcviewer-0.1.2.dist-info/WHEEL
pcviewer-0.1.2.dist-info/top_level.txt
pcviewer-0.1.2.dist-info/RECORD
