Metadata-Version: 2.1
Name: pcviewer
Version: 0.1.2
Summary: A simple tool for visualizing point cloud sequences
Home-page: https://github.com/ziningsong/PCViewer
Author: laowoniu
Author-email: songzn@shanghaitech.edu.cn
License: UNKNOWN
Platform: UNKNOWN
Classifier: Programming Language :: Python :: 3
Classifier: License :: OSI Approved :: MIT License
Classifier: Operating System :: OS Independent
Requires-Python: >=3.7
Requires-Dist: numpy (>=1.19.0)
Requires-Dist: websockets (>=10.0)
Requires-Dist: aiohttp (>=3.8.0)
Requires-Dist: torch (>=1.10.0)
